ArcSet.cp39-win_amd64.pyd
LcsCheck.cp39-win_amd64.pyd
LineSet.cp39-win_amd64.pyd
Polygon.cp39-win_amd64.pyd
Polyline.cp39-win_amd64.pyd
Spatial3dSet.cp39-win_amd64.pyd
SpatialSet.cp39-win_amd64.pyd
Utils.cp39-win_amd64.pyd
ZW_geo-2.230805.dist-info/METADATA
ZW_geo-2.230805.dist-info/WHEEL
ZW_geo-2.230805.dist-info/top_level.txt
ZW_geo-2.230805.dist-info/RECORD
